heat_stroke.py
heat_stroke-0.0.5.dist-info/METADATA
heat_stroke-0.0.5.dist-info/WHEEL
heat_stroke-0.0.5.dist-info/entry_points.txt
heat_stroke-0.0.5.dist-info/top_level.txt
heat_stroke-0.0.5.dist-info/RECORD
